__init__.py
leaping_llm_wrapper.py
leaping_models.py
plugin.py
simpletracer.py
pytest_leaping-0.1.14.dist-info/LICENSE
pytest_leaping-0.1.14.dist-info/METADATA
pytest_leaping-0.1.14.dist-info/WHEEL
pytest_leaping-0.1.14.dist-info/entry_points.txt
pytest_leaping-0.1.14.dist-info/top_level.txt
pytest_leaping-0.1.14.dist-info/RECORD
