Metadata-Version: 2.1
Name: pytest-leaping
Version: 0.1.14
Summary: A simple plugin to use with pytest
Author-email: "Leaping Labs Inc." <founders@leaping.io>
Maintainer-email: "Leaping Labs Inc." <founders@leaping.io>
License: 
Project-URL: Repository, https://github.com/leaping/pytest-leaping
Classifier: Framework :: Pytest
Classifier: Development Status :: 4 - Beta
Classifier: Intended Audience :: Developers
Classifier: Topic :: Software Development :: Testing
Classifier: Operating System :: OS Independent
Classifier: Programming Language :: Python
Classifier: Programming Language :: Python :: 3.8
Classifier: Programming Language :: Python :: 3.9
Classifier: Programming Language :: Python :: 3.10
Classifier: Programming Language :: Python :: 3.11
Classifier: Programming Language :: Python :: 3.12
Classifier: Programming Language :: Python :: 3 :: Only
Classifier: Programming Language :: Python :: Implementation :: CPython
Classifier: Programming Language :: Python :: Implementation :: PyPy
Classifier: License :: OSI Approved :: Apache Software License
Requires-Python: >=3.0
License-File: LICENSE
Requires-Dist: pytest >=6.2.0
Requires-Dist: pexpect ==4.9.0
Requires-Dist: posthog ==3.5.0
Requires-Dist: openai >=1.10.0
Requires-Dist: ollama >=0.1.0
